pypads_onto/__init__.py
pypads_onto/app/__init__.py
pypads_onto/app/actuators.py
pypads_onto/app/api.py
pypads_onto/app/decorators.py
pypads_onto/app/plugin.py
pypads_onto/app/results.py
pypads_onto/app/validators.py
pypads_onto/arguments.py
pypads_onto/bindings/__init__.py
pypads_onto/bindings/anchors.py
pypads_onto/bindings/event_types.py
pypads_onto/bindings/events.py
pypads_onto/bindings/hooks.py
pypads_onto/bindings/resources/__init__.py
pypads_onto/bindings/resources/mapping/__init__.py
pypads_onto/bindings/resources/mapping/sklearn_0_19_1.yml
pypads_onto/bindings/resources/mapping/sklearn_test.yml
pypads_onto/concepts/__init__.py
pypads_onto/injections/__init__.py
pypads_onto/injections/analysis/__init__.py
pypads_onto/injections/converter.py
pypads_onto/injections/loggers/__init__.py
pypads_onto/injections/loggers/uri_tracking.py
pypads_onto/model/__init__.py
pypads_onto/model/ontology.py
pypads_onto/utils/wikibase_util.py
pypads_onto-0.2.2.dist-info/LICENSE
pypads_onto-0.2.2.dist-info/WHEEL
pypads_onto-0.2.2.dist-info/METADATA
pypads_onto-0.2.2.dist-info/RECORD
