Metadata-Version: 2.1
Name: pypads-onto
Version: 0.2.2
Summary: PyPads_Onto is an extension introducing ontology information. It will be used for semantic harmonization.
Home-page: https://www.padre-lab.eu/
License: GPL-3.0-or-later
Keywords: tracking,machine learning,deep learning,neural networks,reproducibility,ontologies,semantic web,linked open data
Author: Thomas Weißgerber
Author-email: thomas.weissgerber@uni-passau.de
Requires-Python: >=3.7.0,<4.0.0
Classifier: Development Status :: 3 - Alpha
Classifier: Intended Audience :: Developers
Classifier: Intended Audience :: Science/Research
Classifier: License :: OSI Approved :: GNU General Public License v3 or later (GPLv3+)
Classifier: Natural Language :: English
Classifier: Operating System :: MacOS
Classifier: Operating System :: Microsoft :: Windows
Classifier: Operating System :: Unix
Classifier: Programming Language :: Python :: 3
Classifier: Programming Language :: Python :: 3.7
Classifier: Programming Language :: Python :: 3.8
Classifier: Programming Language :: Python :: 3.9
Classifier: Topic :: Scientific/Engineering :: Artificial Intelligence
Provides-Extra: docs
Requires-Dist: pypads (>=0.4.0,<0.5.0)
Requires-Dist: rdflib (>=5.0.0,<6.0.0)
Requires-Dist: rdflib-jsonld (>=0.5.0,<0.6.0)
Project-URL: Documentation, https://pypads.readthedocs.io/en/latest/
Project-URL: Repository, https://github.com/padre-lab-eu/pypads-onto
